Version/__init__.py
Version/v1.py
_utils/__init__.py
_utils/_cooltext.py
_utils/_datafile.py
_utils/_print.py
_utils/_rich.py
_utils/_settings.py
_utils/extras.py
_utils/defaults/settings.py
todos/__init__.py
todos/_todo.py
todos/app.py
todos/databaseClass.py
todos/main.py
todos/maindb.py
todos/taskClass.py
user_scripts/__init__.py
user_scripts/reset.py
taskly-0.1.5.dist-info/LICENSE.txt
taskly-0.1.5.dist-info/METADATA
taskly-0.1.5.dist-info/WHEEL
taskly-0.1.5.dist-info/entry_points.txt
taskly-0.1.5.dist-info/top_level.txt
taskly-0.1.5.dist-info/RECORD
