Metadata-Version: 2.1
Name: taskly
Version: 0.1.5
Summary: A CLI based todo app
Author: Talha Ayyaz
Author-email: mtalhaayaz2005@gmail.com
License: MIT
Platform: Mac
Platform: Linux
Classifier: Development Status :: 4 - Beta
Classifier: Programming Language :: Python
License-File: LICENSE.txt
Requires-Dist: importlib-metadata ; python_version < "3.8"
Requires-Dist: rich ; python_version < "3.8"
Requires-Dist: pyfiglet ; python_version < "3.8"
